domain_matcher/__init__.py
domain_matcher/components/__init__.py
domain_matcher/components/hf_manager.py
domain_matcher/components/pipeline.py
domain_matcher/components/topic_modeling.py
domain_matcher/components/training.py
domain_matcher/config.py
domain_matcher/core.py
domain_matcher/experiments.py
domain_matcher/preprocessing.py
domain_matcher/types.py
domain_matcher/utils.py
domain_matcher-0.1.0.dist-info/METADATA
domain_matcher-0.1.0.dist-info/WHEEL
domain_matcher-0.1.0.dist-info/RECORD
