Metadata-Version: 2.1
Name: domain-matcher
Version: 0.1.0
Summary: Protect your models from out of scope domains. Focus on what matters.
License: Apache V2
Author: Dref360
Author-email: fred@glowstick.cx
Requires-Python: >=3.9,<4.0
Classifier: License :: Other/Proprietary License
Classifier: Programming Language :: Python :: 3
Classifier: Programming Language :: Python :: 3.9
Classifier: Programming Language :: Python :: 3.10
Classifier: Programming Language :: Python :: 3.11
Requires-Dist: accelerate (>=0.31.0,<0.32.0)
Requires-Dist: bertopic (>=0.16.2,<0.17.0)
Requires-Dist: datasets (>=2.19.2,<3.0.0)
Requires-Dist: keybert (>=0.8.4,<0.9.0)
Requires-Dist: matplotlib (>=3.9.0,<4.0.0)
Requires-Dist: orjson (>=3.10.3,<4.0.0)
Requires-Dist: pandas (>=2.2.2,<3.0.0)
Requires-Dist: plotly (>=5.22.0,<6.0.0)
Requires-Dist: pydantic (>=2.7.3,<3.0.0)
Requires-Dist: scikit-learn (>=1.5.0,<2.0.0)
Requires-Dist: seaborn (>=0.13.2,<0.14.0)
Requires-Dist: sentence-transformers (>=3.0.1,<4.0.0)
Requires-Dist: structlog (>=24.2.0,<25.0.0)
Requires-Dist: tensorboard (>=2.17.0,<3.0.0)
Requires-Dist: torch (>=2.3.1,<3.0.0)
Requires-Dist: transformers (>=4.41.2,<5.0.0)
Requires-Dist: typer[all] (>=0.12.3,<0.13.0)
